{
  "minecraft:recipes/tools/fishing_rod": {
    "criteria": {
      "has_string": "2022-06-16 08:24:05 -0400"
    },
    "done": true
  },
  "minecraft:recipes/building_blocks/yellow_terracotta": {
    "criteria": {
      "has_terracotta": "2022-06-16 08:22:03 -0400"
    },
    "done": true
  },
  "minecraft:recipes/decorations/smoker": {
    "criteria": {
      "has_furnace": "2022-06-16 08:29:11 -0400"
    },
    "done": true
  },
  "minecraft:recipes/tools/wooden_axe": {
    "criteria": {
      "has_stick": "2022-06-16 08:23:18 -0400"
    },
    "done": true
  },
  "minecraft:recipes/redstone/lever": {
    "criteria": {
      "has_cobblestone": "2022-06-16 08:22:03 -0400"
    },
    "done": true
  },
  "minecraft:recipes/building_blocks/purple_terracotta": {
    "criteria": {
      "has_terracotta": "2022-06-16 08:22:03 -0400"
    },
    "done": true
  },
  "minecraft:recipes/building_blocks/cobblestone_stairs_from_cobblestone_stonecutting": {
    "criteria": {
      "has_cobblestone": "2022-06-16 08:22:03 -0400"
    },
    "done": true
  },
  "minecraft:recipes/redstone/jungle_pressure_plate": {
    "criteria": {
      "has_planks": "2022-06-16 08:20:28 -0400"
    },
    "done": true
  },
  "minecraft:recipes/combat/iron_sword": {
    "criteria": {
      "has_iron_ingot": "2022-06-16 08:35:29 -0400"
    },
    "done": true
  },
  "minecraft:recipes/food/cooked_salmon_from_smoking": {
    "criteria": {
      "has_salmon": "2022-06-16 08:27:51 -0400"
    },
    "done": true
  },
  "minecraft:recipes/decorations/loom": {
    "criteria": {
      "has_string": "2022-06-16 08:24:05 -0400"
    },
    "done": true
  },
  "minecraft:recipes/misc/iron_ingot_from_blasting_raw_iron": {
    "criteria": {
      "has_raw_iron": "2022-06-16 08:31:32 -0400"
    },
    "done": true
  },
  "minecraft:recipes/tools/iron_pickaxe": {
    "criteria": {
      "has_iron_ingot": "2022-06-16 08:35:29 -0400"
    },
    "done": true
  },
  "minecraft:recipes/decorations/crafting_table": {
    "criteria": {
      "has_planks": "2022-06-16 08:20:28 -0400"
    },
    "done": true
  },
  "minecraft:recipes/decorations/campfire": {
    "criteria": {
      "has_stick": "2022-06-16 08:23:18 -0400"
    },
    "done": true
  },
  "minecraft:recipes/decorations/candle": {
    "criteria": {
      "has_string": "2022-06-16 08:24:05 -0400"
    },
    "done": true
  },
  "minecraft:recipes/decorations/ladder": {
    "criteria": {
      "has_stick": "2022-06-16 08:23:18 -0400"
    },
    "done": true
  },
  "minecraft:recipes/misc/iron_nugget": {
    "criteria": {
      "has_iron_ingot": "2022-06-16 08:35:29 -0400"
    },
    "done": true
  },
  "minecraft:recipes/decorations/chest": {
    "criteria": {
      "has_lots_of_items": "2022-06-16 08:22:03 -0400"
    },
    "done": true
  },
  "minecraft:recipes/building_blocks/iron_block": {
    "criteria": {
      "has_iron_ingot": "2022-06-16 08:35:29 -0400"
    },
    "done": true
  },
  "minecraft:recipes/transportation/mangrove_boat": {
    "criteria": {
      "in_water": "2022-06-16 08:26:05 -0400"
    },
    "done": true
  },
  "minecraft:recipes/tools/wooden_shovel": {
    "criteria": {
      "has_stick": "2022-06-16 08:23:18 -0400"
    },
    "done": true
  },
  "minecraft:recipes/decorations/torch": {
    "criteria": {
      "has_stone_pickaxe": "2022-06-16 08:23:30 -0400"
    },
    "done": true
  },
  "minecraft:recipes/building_blocks/red_terracotta": {
    "criteria": {
      "has_terracotta": "2022-06-16 08:22:03 -0400"
    },
    "done": true
  },
  "minecraft:recipes/building_blocks/jungle_wood": {
    "criteria": {
      "has_log": "2022-06-16 08:20:02 -0400"
    },
    "done": true
  },
  "minecraft:recipes/tools/shears": {
    "criteria": {
      "has_iron_ingot": "2022-06-16 08:35:29 -0400"
    },
    "done": true
  },
  "minecraft:recipes/misc/stick": {
    "criteria": {
      "has_planks": "2022-06-16 08:20:28 -0400"
    },
    "done": true
  },
  "minecraft:recipes/transportation/spruce_boat": {
    "criteria": {
      "in_water": "2022-06-16 08:26:05 -0400"
    },
    "done": true
  },
  "minecraft:recipes/tools/stone_shovel": {
    "criteria": {
      "has_cobblestone": "2022-06-16 08:22:03 -0400"
    },
    "done": true
  },
  "minecraft:recipes/combat/wooden_sword": {
    "criteria": {
      "has_stick": "2022-06-16 08:23:18 -0400"
    },
    "done": true
  },
  "minecraft:recipes/misc/firework_rocket_simple": {
    "criteria": {
      "has_gunpowder": "2022-06-16 08:21:03 -0400"
    },
    "done": true
  },
  "minecraft:recipes/building_blocks/oak_planks": {
    "criteria": {
      "has_logs": "2022-06-16 08:21:00 -0400"
    },
    "done": true
  },
  "minecraft:recipes/redstone/dispenser": {
    "criteria": {
      "has_bow": "2022-06-16 08:25:07 -0400"
    },
    "done": true
  },
  "minecraft:recipes/building_blocks/lime_terracotta": {
    "criteria": {
      "has_terracotta": "2022-06-16 08:22:03 -0400"
    },
    "done": true
  },
  "minecraft:recipes/building_blocks/green_terracotta": {
    "criteria": {
      "has_terracotta": "2022-06-16 08:22:03 -0400"
    },
    "done": true
  },
  "minecraft:recipes/decorations/jungle_sign": {
    "criteria": {
      "has_planks": "2022-06-16 08:20:28 -0400"
    },
    "done": true
  },
  "minecraft:recipes/combat/iron_leggings": {
    "criteria": {
      "has_iron_ingot": "2022-06-16 08:35:29 -0400"
    },
    "done": true
  },
  "minecraft:recipes/building_blocks/gray_terracotta": {
    "criteria": {
      "has_terracotta": "2022-06-16 08:22:03 -0400"
    },
    "done": true
  },
  "minecraft:husbandry/balanced_diet": {
    "criteria": {
      "rotten_flesh": "2022-06-16 08:26:50 -0400",
      "cooked_salmon": "2022-06-16 08:29:26 -0400"
    },
    "done": false
  },
  "minecraft:recipes/tools/iron_axe": {
    "criteria": {
      "has_iron_ingot": "2022-06-16 08:35:29 -0400"
    },
    "done": true
  },
  "minecraft:recipes/building_blocks/light_gray_terracotta": {
    "criteria": {
      "has_terracotta": "2022-06-16 08:22:03 -0400"
    },
    "done": true
  },
  "minecraft:recipes/building_blocks/brown_terracotta": {
    "criteria": {
      "has_terracotta": "2022-06-16 08:22:03 -0400"
    },
    "done": true
  },
  "minecraft:recipes/redstone/jungle_trapdoor": {
    "criteria": {
      "has_planks": "2022-06-16 08:20:28 -0400"
    },
    "done": true
  },
  "minecraft:recipes/tools/wooden_hoe": {
    "criteria": {
      "has_stick": "2022-06-16 08:23:18 -0400"
    },
    "done": true
  },
  "minecraft:recipes/combat/shield": {
    "criteria": {
      "has_iron_ingot": "2022-06-16 08:35:29 -0400"
    },
    "done": true
  },
  "minecraft:recipes/building_blocks/jungle_planks": {
    "criteria": {
      "has_logs": "2022-06-16 08:20:02 -0400"
    },
    "done": true
  },
  "minecraft:recipes/building_blocks/cobblestone_slab": {
    "criteria": {
      "has_cobblestone": "2022-06-16 08:22:03 -0400"
    },
    "done": true
  },
  "minecraft:recipes/redstone/tripwire_hook": {
    "criteria": {
      "has_string": "2022-06-16 08:24:05 -0400"
    },
    "done": true
  },
  "minecraft:recipes/misc/bucket": {
    "criteria": {
      "has_iron_ingot": "2022-06-16 08:35:29 -0400"
    },
    "done": true
  },
  "minecraft:recipes/redstone/jungle_button": {
    "criteria": {
      "has_planks": "2022-06-16 08:20:28 -0400"
    },
    "done": true
  },
  "minecraft:recipes/combat/iron_boots": {
    "criteria": {
      "has_iron_ingot": "2022-06-16 08:35:29 -0400"
    },
    "done": true
  },
  "minecraft:recipes/misc/bone_meal": {
    "criteria": {
      "has_bone": "2022-06-16 08:22:02 -0400"
    },
    "done": true
  },
  "minecraft:recipes/building_blocks/cobblestone_stairs": {
    "criteria": {
      "has_cobblestone": "2022-06-16 08:22:03 -0400"
    },
    "done": true
  },
  "minecraft:recipes/redstone/hopper": {
    "criteria": {
      "has_iron_ingot": "2022-06-16 08:35:29 -0400"
    },
    "done": true
  },
  "minecraft:recipes/building_blocks/pink_terracotta": {
    "criteria": {
      "has_terracotta": "2022-06-16 08:22:03 -0400"
    },
    "done": true
  },
  "minecraft:recipes/building_blocks/black_terracotta": {
    "criteria": {
      "has_terracotta": "2022-06-16 08:22:03 -0400"
    },
    "done": true
  },
  "minecraft:recipes/building_blocks/oak_wood": {
    "criteria": {
      "has_log": "2022-06-16 08:35:51 -0400"
    },
    "done": true
  },
  "minecraft:recipes/food/cooked_salmon": {
    "criteria": {
      "has_salmon": "2022-06-16 08:27:51 -0400"
    },
    "done": true
  },
  "minecraft:story/root": {
    "criteria": {
      "crafting_table": "2022-06-16 08:22:03 -0400"
    },
    "done": true
  },
  "minecraft:recipes/combat/crossbow": {
    "criteria": {
      "has_stick": "2022-06-16 08:23:18 -0400"
    },
    "done": true
  },
  "minecraft:recipes/combat/iron_chestplate": {
    "criteria": {
      "has_iron_ingot": "2022-06-16 08:35:29 -0400"
    },
    "done": true
  },
  "minecraft:recipes/building_blocks/magenta_terracotta": {
    "criteria": {
      "has_terracotta": "2022-06-16 08:22:03 -0400"
    },
    "done": true
  },
  "minecraft:recipes/building_blocks/orange_terracotta": {
    "criteria": {
      "has_terracotta": "2022-06-16 08:22:03 -0400"
    },
    "done": true
  },
  "minecraft:recipes/combat/iron_helmet": {
    "criteria": {
      "has_iron_ingot": "2022-06-16 08:35:29 -0400"
    },
    "done": true
  },
  "minecraft:recipes/building_blocks/jungle_slab": {
    "criteria": {
      "has_planks": "2022-06-16 08:20:28 -0400"
    },
    "done": true
  },
  "minecraft:recipes/combat/bow": {
    "criteria": {
      "has_string": "2022-06-16 08:24:05 -0400"
    },
    "done": true
  },
  "minecraft:recipes/redstone/tnt": {
    "criteria": {
      "has_gunpowder": "2022-06-16 08:21:03 -0400"
    },
    "done": true
  },
  "minecraft:adventure/kill_a_mob": {
    "criteria": {
      "minecraft:skeleton": "2022-06-16 08:21:51 -0400"
    },
    "done": true
  },
  "minecraft:recipes/building_blocks/blue_terracotta": {
    "criteria": {
      "has_terracotta": "2022-06-16 08:22:03 -0400"
    },
    "done": true
  },
  "minecraft:recipes/decorations/iron_bars": {
    "criteria": {
      "has_iron_ingot": "2022-06-16 08:35:29 -0400"
    },
    "done": true
  },
  "minecraft:story/mine_stone": {
    "criteria": {
      "get_stone": "2022-06-16 08:22:03 -0400"
    },
    "done": true
  },
  "minecraft:recipes/building_blocks/stone": {
    "criteria": {
      "has_cobblestone": "2022-06-16 08:22:03 -0400"
    },
    "done": true
  },
  "minecraft:recipes/decorations/furnace": {
    "criteria": {
      "has_cobblestone": "2022-06-16 08:22:03 -0400"
    },
    "done": true
  },
  "minecraft:recipes/transportation/minecart": {
    "criteria": {
      "has_iron_ingot": "2022-06-16 08:35:29 -0400"
    },
    "done": true
  },
  "minecraft:recipes/building_blocks/light_blue_terracotta": {
    "criteria": {
      "has_terracotta": "2022-06-16 08:22:03 -0400"
    },
    "done": true
  },
  "minecraft:adventure/adventuring_time": {
    "criteria": {
      "minecraft:birch_forest": "2022-06-16 08:04:19 -0400",
      "minecraft:bamboo_jungle": "2022-06-16 08:28:17 -0400",
      "minecraft:beach": "2022-06-16 08:05:41 -0400",
      "minecraft:lukewarm_ocean": "2022-06-16 08:27:55 -0400",
      "minecraft:river": "2022-06-16 08:27:45 -0400",
      "minecraft:jungle": "2022-06-16 08:04:33 -0400",
      "minecraft:windswept_savanna": "2022-06-16 08:04:56 -0400"
    },
    "done": false
  },
  "minecraft:recipes/redstone/iron_door": {
    "criteria": {
      "has_iron_ingot": "2022-06-16 08:35:29 -0400"
    },
    "done": true
  },
  "minecraft:recipes/misc/charcoal": {
    "criteria": {
      "has_log": "2022-06-16 08:20:02 -0400"
    },
    "done": true
  },
  "minecraft:recipes/tools/wooden_pickaxe": {
    "criteria": {
      "has_stick": "2022-06-16 08:23:18 -0400"
    },
    "done": true
  },
  "minecraft:recipes/tools/iron_hoe": {
    "criteria": {
      "has_iron_ingot": "2022-06-16 08:35:29 -0400"
    },
    "done": true
  },
  "minecraft:recipes/building_blocks/cobblestone_slab_from_cobblestone_stonecutting": {
    "criteria": {
      "has_cobblestone": "2022-06-16 08:22:03 -0400"
    },
    "done": true
  },
  "minecraft:husbandry/root": {
    "criteria": {
      "consumed_item": "2022-06-16 08:26:50 -0400"
    },
    "done": true
  },
  "minecraft:recipes/transportation/birch_boat": {
    "criteria": {
      "in_water": "2022-06-16 08:26:05 -0400"
    },
    "done": true
  },
  "minecraft:recipes/combat/stone_sword": {
    "criteria": {
      "has_cobblestone": "2022-06-16 08:22:03 -0400"
    },
    "done": true
  },
  "minecraft:recipes/decorations/barrel": {
    "criteria": {
      "has_planks": "2022-06-16 08:20:28 -0400"
    },
    "done": true
  },
  "minecraft:recipes/decorations/cobblestone_wall": {
    "criteria": {
      "has_cobblestone": "2022-06-16 08:22:03 -0400"
    },
    "done": true
  },
  "minecraft:recipes/brewing/fermented_spider_eye": {
    "criteria": {
      "has_spider_eye": "2022-06-16 08:24:27 -0400"
    },
    "done": true
  },
  "minecraft:recipes/transportation/acacia_boat": {
    "criteria": {
      "in_water": "2022-06-16 08:26:05 -0400"
    },
    "done": true
  },
  "minecraft:recipes/misc/iron_ingot_from_smelting_raw_iron": {
    "criteria": {
      "has_raw_iron": "2022-06-16 08:31:32 -0400"
    },
    "done": true
  },
  "minecraft:recipes/tools/iron_shovel": {
    "criteria": {
      "has_iron_ingot": "2022-06-16 08:35:29 -0400"
    },
    "done": true
  },
  "minecraft:recipes/tools/stone_pickaxe": {
    "criteria": {
      "has_cobblestone": "2022-06-16 08:22:03 -0400"
    },
    "done": true
  },
  "minecraft:recipes/redstone/iron_trapdoor": {
    "criteria": {
      "has_iron_ingot": "2022-06-16 08:35:29 -0400"
    },
    "done": true
  },
  "minecraft:recipes/decorations/smithing_table": {
    "criteria": {
      "has_iron_ingot": "2022-06-16 08:35:29 -0400"
    },
    "done": true
  },
  "minecraft:adventure/root": {
    "criteria": {
      "killed_by_something": "2022-06-16 08:21:27 -0400"
    },
    "done": true
  },
  "minecraft:recipes/transportation/jungle_boat": {
    "criteria": {
      "in_water": "2022-06-16 08:26:05 -0400"
    },
    "done": true
  },
  "minecraft:recipes/decorations/cobblestone_wall_from_cobblestone_stonecutting": {
    "criteria": {
      "has_cobblestone": "2022-06-16 08:22:03 -0400"
    },
    "done": true
  },
  "minecraft:recipes/food/cooked_salmon_from_campfire_cooking": {
    "criteria": {
      "has_salmon": "2022-06-16 08:27:51 -0400"
    },
    "done": true
  },
  "minecraft:recipes/building_blocks/jungle_stairs": {
    "criteria": {
      "has_planks": "2022-06-16 08:20:28 -0400"
    },
    "done": true
  },
  "minecraft:recipes/decorations/jungle_fence": {
    "criteria": {
      "has_planks": "2022-06-16 08:20:28 -0400"
    },
    "done": true
  },
  "minecraft:recipes/redstone/heavy_weighted_pressure_plate": {
    "criteria": {
      "has_iron_ingot": "2022-06-16 08:35:29 -0400"
    },
    "done": true
  },
  "minecraft:recipes/tools/stone_hoe": {
    "criteria": {
      "has_cobblestone": "2022-06-16 08:22:03 -0400"
    },
    "done": true
  },
  "minecraft:recipes/building_blocks/white_wool_from_string": {
    "criteria": {
      "has_string": "2022-06-16 08:24:05 -0400"
    },
    "done": true
  },
  "minecraft:recipes/transportation/dark_oak_boat": {
    "criteria": {
      "in_water": "2022-06-16 08:26:05 -0400"
    },
    "done": true
  },
  "minecraft:recipes/redstone/jungle_door": {
    "criteria": {
      "has_planks": "2022-06-16 08:20:28 -0400"
    },
    "done": true
  },
  "minecraft:adventure/kill_all_mobs": {
    "criteria": {
      "minecraft:skeleton": "2022-06-16 08:21:51 -0400",
      "minecraft:spider": "2022-06-16 08:24:04 -0400",
      "minecraft:zombie": "2022-06-16 08:25:17 -0400"
    },
    "done": false
  },
  "minecraft:recipes/redstone/jungle_fence_gate": {
    "criteria": {
      "has_planks": "2022-06-16 08:20:28 -0400"
    },
    "done": true
  },
  "minecraft:recipes/decorations/lantern": {
    "criteria": {
      "has_iron_ingot": "2022-06-16 08:35:29 -0400"
    },
    "done": true
  },
  "minecraft:recipes/food/cookie": {
    "criteria": {
      "has_cocoa": "2022-06-16 08:26:59 -0400"
    },
    "done": true
  },
  "minecraft:recipes/decorations/chain": {
    "criteria": {
      "has_iron_ingot": "2022-06-16 08:35:29 -0400"
    },
    "done": true
  },
  "minecraft:recipes/building_blocks/cyan_terracotta": {
    "criteria": {
      "has_terracotta": "2022-06-16 08:22:03 -0400"
    },
    "done": true
  },
  "minecraft:story/upgrade_tools": {
    "criteria": {
      "stone_pickaxe": "2022-06-16 08:23:30 -0400"
    },
    "done": true
  },
  "minecraft:recipes/building_blocks/white_terracotta": {
    "criteria": {
      "has_terracotta": "2022-06-16 08:22:03 -0400"
    },
    "done": true
  },
  "minecraft:recipes/decorations/soul_campfire": {
    "criteria": {
      "has_stick": "2022-06-16 08:23:18 -0400"
    },
    "done": true
  },
  "minecraft:recipes/transportation/oak_boat": {
    "criteria": {
      "in_water": "2022-06-16 08:26:05 -0400"
    },
    "done": true
  },
  "minecraft:story/smelt_iron": {
    "criteria": {
      "iron": "2022-06-16 08:35:29 -0400"
    },
    "done": true
  },
  "minecraft:recipes/tools/stone_axe": {
    "criteria": {
      "has_cobblestone": "2022-06-16 08:22:03 -0400"
    },
    "done": true
  },
  "minecraft:recipes/misc/brown_dye": {
    "criteria": {
      "has_cocoa_beans": "2022-06-16 08:26:59 -0400"
    },
    "done": true
  },
  "minecraft:recipes/building_blocks/raw_iron_block": {
    "criteria": {
      "has_raw_iron": "2022-06-16 08:31:32 -0400"
    },
    "done": true
  },
  "DataVersion": 3105
}